kladama/__init__.py
kladama/context.py
kladama/entities.py
kladama/loader.py
kladama/queries.py
kladama/services.py
kladama/transactions.py
kladama/web.py
kladama_api-1.1.0.dist-info/LICENSE
kladama_api-1.1.0.dist-info/METADATA
kladama_api-1.1.0.dist-info/WHEEL
kladama_api-1.1.0.dist-info/top_level.txt
kladama_api-1.1.0.dist-info/RECORD
