Metadata-Version: 2.1
Name: kladama-api
Version: 1.1.0
Summary: Kladama API package
Home-page: https://github.com/plexilar/kladama-api-python
Author: Plexilar
Author-email: hdkrus@gmail.com
License: UNKNOWN
Keywords: kladama api
Platform: UNKNOWN
Classifier: Programming Language :: Python :: 3
Classifier: Development Status :: 5 - Production/Stable
Classifier: Intended Audience :: Developers
Classifier: Topic :: Software Development :: Libraries :: Python Modules
Classifier: License :: OSI Approved :: MIT License
Classifier: Operating System :: OS Independent
Requires-Python: >=3.6
Requires-Dist: jsonlib-python3
Requires-Dist: requests
